AUTHORS
LICENSE
MANIFEST.in
README.md
requirements.txt
run_tests.py
setup.cfg
setup.py
test_requirements.txt
config/dpkg/changelog
config/dpkg/clean
config/dpkg/compat
config/dpkg/control
config/dpkg/copyright
config/dpkg/python3-timesketch.install
config/dpkg/rules
config/dpkg/timesketch-data.dirs
config/dpkg/timesketch-data.install
config/dpkg/timesketch-server.dirs
config/dpkg/timesketch-server.install
config/dpkg/timesketch-server.postinst
config/dpkg/timesketch-server.timesketch.default
config/dpkg/timesketch-server.timesketch.service
config/dpkg/timesketch-server.timesketch.socket
config/dpkg/source/format
data/bigquery_matcher.yaml
data/context_links.yaml
data/data_finder.yaml
data/generic.mappings
data/gunicorn_config.py
data/intelligence_tag_metadata.yaml
data/ontology.yaml
data/plaso.mappings
data/plaso_formatters.yaml
data/regex_features.yaml
data/sigma_config.yaml
data/tags.yaml
data/timesketch.conf
data/winevt_features.yaml
data/yeti-prod.crt
data/dfiq/README.md
data/llm_summarize/prompt.txt
data/llm_summarize/prompt_llm_synthesize.txt
data/nl2q/data_types.csv
data/nl2q/examples_nl2q
data/nl2q/prompt_nl2q
data/sigma/lnx_apt_equationgroup_lnx.yml
data/sigma/lnx_auth_pwnkit_local_privilege_escalation.yml
data/sigma/lnx_buffer_overflows.yml
data/sigma/lnx_clear_syslog.yml
data/sigma/lnx_file_copy.yml
data/sigma/lnx_ldso_preload_injection.yml
data/sigma/lnx_nimbuspwn_privilege_escalation_exploit.yml
data/sigma/lnx_potential_susp_ebpf_activity.yml
data/sigma/lnx_privileged_user_creation.yml
data/sigma/lnx_shell_clear_cmd_history.yml
data/sigma/lnx_shell_susp_commands.yml
data/sigma/lnx_shell_susp_log_entries.yml
data/sigma/lnx_shell_susp_rev_shells.yml
data/sigma/lnx_shellshock.yml
data/sigma/lnx_space_after_filename_.yml
data/sigma/lnx_sshd_ssh_cve_2018_15473.yml
data/sigma/lnx_sshd_susp_ssh.yml
data/sigma/lnx_susp_dev_tcp.yml
data/sigma/lnx_susp_jexboss.yml
data/sigma/lnx_symlink_etc_passwd.yml
data/sigma/lnx_syslog_security_tools_disabling_syslog.yml
timesketch.egg-info/PKG-INFO
timesketch.egg-info/SOURCES.txt
timesketch.egg-info/dependency_links.txt
timesketch.egg-info/entry_points.txt
timesketch.egg-info/not-zip-safe
timesketch.egg-info/top_level.txt
