Metadata-Version: 2.4
Name: timesketch
Version: 20260119
Summary: Digital forensic timeline analysis
Home-page: http://www.timesketch.org/
Maintainer: Timesketch development team
Maintainer-email: timesketch-dev@googlegroups.com
License: Apache License, Version 2.0
Classifier: Development Status :: 4 - Beta
Classifier: Environment :: Web Environment
Classifier: Operating System :: OS Independent
Classifier: Programming Language :: Python
License-File: LICENSE
Dynamic: classifier
Dynamic: description
Dynamic: home-page
Dynamic: license
Dynamic: license-file
Dynamic: maintainer
Dynamic: maintainer-email
Dynamic: summary
